textprepender/__init__.py
textprepender/__main__.py
text_prepender-0.1.0.dist-info/LICENSE
text_prepender-0.1.0.dist-info/METADATA
text_prepender-0.1.0.dist-info/NOTICE
text_prepender-0.1.0.dist-info/WHEEL
text_prepender-0.1.0.dist-info/entry_points.txt
text_prepender-0.1.0.dist-info/top_level.txt
text_prepender-0.1.0.dist-info/RECORD
