Metadata-Version: 2.1
Name: text-prepender
Version: 0.1.0
Summary: Add text (like legal text) to the top of code without breaking it.
Home-page: https://github.com/dontirun/text-prepender
Author: Arun Donti
Author-email: dontirun@gmail.com
License: MIT
Project-URL: Bug Tracker, https://github.com/dontirun/text-prepender/issues
Platform: UNKNOWN
Classifier: Development Status :: 5 - Production/Stable
Classifier: Intended Audience :: Developers
Classifier: License :: OSI Approved :: MIT License
Classifier: Natural Language :: English
Classifier: Operating System :: OS Independent
Classifier: Programming Language :: Python :: 2
Classifier: Programming Language :: Python :: 2.7
Classifier: Programming Language :: Python :: 3
Classifier: Programming Language :: Python :: 3.5
Classifier: Programming Language :: Python :: 3.6
Classifier: Programming Language :: Python :: 3.7
Classifier: Programming Language :: Python :: 3.8
Classifier: Programming Language :: Python :: 3.9
Requires-Python: >=2.7, !=3.0.*, !=3.1.*, !=3.2.*, !=3.3.*
License-File: LICENSE
License-File: NOTICE
